birdwell/database/__init__.py
birdwell/database/base.py
birdwell/database/crypto.py
birdwell/database/mapped.py
birdwell/database/models.py
birdwell_database-1.3.3rc12.dev1.dist-info/LICENSE
birdwell_database-1.3.3rc12.dev1.dist-info/METADATA
birdwell_database-1.3.3rc12.dev1.dist-info/WHEEL
birdwell_database-1.3.3rc12.dev1.dist-info/top_level.txt
birdwell_database-1.3.3rc12.dev1.dist-info/RECORD
