Metadata-Version: 2.1
Name: birdwell-database
Version: 1.3.3rc12.dev1
Summary: database submodule of the birdwell namespace package
Author-email: jcbirdwell <jcbirdwell@gmail.com>
License: MIT License
Classifier: Development Status :: 3 - Alpha
Requires-Python: >=3.10
License-File: LICENSE
Requires-Dist: psycopg[pool]
Provides-Extra: crypto
Requires-Dist: cryptography ; extra == 'crypto'
